[{"ticker":"PUNK","addr":"0x269616d549d7e8eaa82dfb17028d0b212d11232a","totalFeesEarned":"1.11","totalFeesClaimed":"0.75","totalFeesLost":"0.16","totalFeesOwed":"0.61","totalLuckyStakers":7,"totalStakersOwed":20},{"ticker":"AVASTR","addr":"0xdcdc1c1cc33aa817cbdbe8f5e2390bf7cc43dc4b","totalFeesEarned":"26.26","totalFeesClaimed":"5.55","totalFeesLost":"0.67","totalFeesOwed":"21.21","totalLuckyStakers":1,"totalStakersOwed":12},{"ticker":"KITTY","addr":"0x9b9fb226e98c4e90db2830c9aefa9cfcbe3b000a","totalFeesEarned":"4.45","totalFeesClaimed":"1.16","totalFeesLost":"0.16","totalFeesOwed":"3.31","totalLuckyStakers":1,"totalStakersOwed":3},{"ticker":"MASK","addr":"0xc7a8b45e184138114e6085c82936a8db93dd156a","totalFeesEarned":"4.42","totalFeesClaimed":"3.36","totalFeesLost":"0.50","totalFeesOwed":"1.11","totalLuckyStakers":1,"totalStakersOwed":6},{"ticker":"BAKC","addr":"0xe632e1ea781df32c60ab11052958744cbfbc439a","totalFeesEarned":"0.84","totalFeesClaimed":"0.21","totalFeesLost":"0.03","totalFeesOwed":"0.66","totalLuckyStakers":2,"totalStakersOwed":3},{"ticker":"WIZARD","addr":"0x87931e7ad81914e7898d07c68f145fc0a553d8fb","totalFeesEarned":"12.12","totalFeesClaimed":"1.13","totalFeesLost":"0.84","totalFeesOwed":"12.12","totalLuckyStakers":1,"totalStakersOwed":7},{"ticker":"PUPS","addr":"0xd53998c536fc8b59b38aa0b49dbd8170d5ebf4c2","totalFeesEarned":"0.39","totalFeesClaimed":"0.07","totalFeesLost":"0.05","totalFeesOwed":"0.37","totalLuckyStakers":1,"totalStakersOwed":2},{"ticker":"BERRY","addr":"0xe944f2b46fcfc9d0e887bbeaad95268d9416d0fd","totalFeesEarned":"0.89","totalFeesClaimed":"0.001","totalFeesLost":"0.001","totalFeesOwed":"0.89","totalLuckyStakers":1,"totalStakersOwed":4},{"ticker":"META","addr":"0x2f5c3dd519e8a502c48c9fc104eee64fdff05f03","totalFeesEarned":"1.14","totalFeesClaimed":"0.02","totalFeesLost":"0.02","totalFeesOwed":"1.14","totalLuckyStakers":1,"totalStakersOwed":6},{"ticker":"KAMAX","addr":"0xb2c62e0a1f5837356e399359ecc34fcc49a02093","totalFeesEarned":"0.94","totalFeesClaimed":"0.42","totalFeesLost":"0.18","totalFeesOwed":"0.71","totalLuckyStakers":1,"totalStakersOwed":2},{"ticker":"GSA","addr":"0xefe2eadf814179d93651e07607d661d2953cd55f","totalFeesEarned":"2.21","totalFeesClaimed":"0.0","totalFeesLost":"0.16","totalFeesOwed":"2.23","totalLuckyStakers":1,"totalStakersOwed":4},{"ticker":"CYPHER","addr":"0x62c30556fde78b3423075758dc3fb74e2eccbfe4","totalFeesEarned":"4.46","totalFeesClaimed":"0.001","totalFeesLost":"0.20","totalFeesOwed":"4.48","totalLuckyStakers":2,"totalStakersOwed":7},{"ticker":"DUDE","addr":"0xaebfaa45f98b655f85fdd6df3dc8e9c073a59779","totalFeesEarned":"2.20","totalFeesClaimed":"0.83","totalFeesLost":"0.08","totalFeesOwed":"1.12","totalLuckyStakers":2,"totalStakersOwed":8},{"ticker":"PARALLEL","addr":"0x4304940f12f9740ffce4124d0e2ec1340cc6f349","totalFeesEarned":"0.29","totalFeesClaimed":"0.11","totalFeesLost":"0.001","totalFeesOwed":"0.18","totalLuckyStakers":1,"totalStakersOwed":1}]